<?xml version="1.0" standalone="yes"?>
<TrackManager>
	<Language>
		<Form Name="frmTrackManager">
			<Object Name="mnuMainFile" Type="Menu">Bestand</Object>
			<Object Name="mnuMainFileLogOff" Type="Menu">Uitloggen</Object>
			<Object Name="mnuMainFileReload" Type="Menu">Herstarten</Object>
			<Object Name="mnuMainFileExit" Type="Menu">Afsluiten</Object>
			<Object Name="mnuMainEdit" Type="Menu">Bewerken</Object>
			<Object Name="mnuMainEditDay" Type="Menu">(De)Blokkeer Dag</Object>
			<Object Name="mnuMainEditTrack" Type="Menu">(De)Blokkeer Baan</Object>
			<Object Name="mnuMainEditHour" Type="Menu">(De)Blokkeer Les</Object>
			<Object Name="mnuMainEditScreen" Type="Menu">Bewaar Scherm positie</Object>
			<Object Name="mnuMainWindow" Type="Menu">Venster</Object>
			<Object Name="mnuMainWindowSettings" Type="Menu">Instellingen</Object>
			<Object Name="mnuMainWindowSecurity" Type="Menu">Beveiliging</Object>
			<Object Name="mnuMainHelp" Type="Menu">Help</Object>
			<Object Name="mnuMainHelpManual" Type="Menu">Handleiding</Object>
			<Object Name="mnuMainHelpAbout" Type="Menu">Over TrackManager</Object>

			<Object Name="lvwAppClients_colAppClient" Type="List">Klant</Object>
			<Object Name="lvwAppClients_colAppLessonType" Type="List">Les Type</Object>
			<Object Name="lvwAppClients_colAppLessonCount" Type="List">Aantal</Object>

			<Object Name="btnMemoSave" Type="Text">Memo Opslaan</Object>
			<Object Name="lblStatus" Type="Text">Status</Object>
			<Object Name="grpAppDetails" Type="Text">Afspraak Details</Object>
			<Object Name="btnAppRemove" Type="Text">Verwijder uit Lijst</Object>
			<Object Name="btnAppClear" Type="Text">Lijst Wissen</Object>
			<Object Name="btnAppDelete" Type="Text">Afspraak Verwijderen</Object>
			<Object Name="btnAppMove" Type="Text">Afspraak Verplaatsen</Object>
			<Object Name="btnAppCreate" Type="Text">Afspraak Maken</Object>
			<Object Name="lblAppDetailsTrack" Type="Text">Baan</Object>
			<Object Name="lblAppDetailsTime" Type="Text">Tijd</Object>
			<Object Name="lblAppDetailsDate" Type="Text">Datum</Object>
			<Object Name="grpCurrentSelection" Type="Text">Huidige Selectie</Object>
			<Object Name="lblCurrentSelectionClient" Type="Text">Klant</Object>
			<Object Name="lblCurrentSelectionGroup" Type="Text">Groep</Object>

			<Object Name="tpgTracks" Type="Text">Banen</Object>
			<Object Name="lblTracksBar" Type="Text">Bar</Object>
			<Object Name="lblTrackTeacher" Type="Text">Leraar</Object>
			<Object Name="lblTrackClient" Type="Text">Klant</Object>

			<Object Name="tpgGroups" Type="Text">Groepen</Object>
			<Object Name="lvwGroups_colGroupName" Type="List">Groep Naam</Object>
			<Object Name="lvwGroups_colGroupNumber" Type="List">Groep Nummer</Object>

			<Object Name="grpGroupMembers" Type="Text">Groep Leden</Object>
			<Object Name="lblGroupLessonsTotal" Type="Text">Totaal Aantal</Object>
			<Object Name="lblGroupLessonsBilled" Type="Text">Gefactureerd</Object>
			<Object Name="lblGroupClientLevel" Type="Text">Klant Niveau</Object>
			<Object Name="lblGroupExtraCount" Type="Text">Extra Niveau</Object>
			<Object Name="lblGroupLessonCount" Type="Text">Lessen Aantal</Object>
			<Object Name="lblGroupLessonType" Type="Text">Les Type</Object>
			<Object Name="lblGroupsFullName" Type="Text">Klant Naam</Object>
			<Object Name="btnGrpAppClear" Type="Text">Lijst Wissen</Object>
			<Object Name="btnGrpAppRemove" Type="Text">Verwijder van Afspraak</Object>
			<Object Name="btnGrpAppAdd" Type="Text">Voeg toe aan Afspraak</Object>
			<Object Name="btnGroupUpdateLevel" Type="Text">Klant Opslaan</Object>
			<Object Name="grpMainContact" Type="Text">Primair Contact</Object>
			<Object Name="btnGroupsMainContact" Type="Text">Instellen als Primair Contact</Object>
			<Object Name="btnGroupEditClient" Type="Text">Klanten Beheren</Object>
			<Object Name="btnGroupManage" Type="Text">Groepen Beheren</Object>

			<Object Name="tpgFinance" Type="Text">Financien</Object>
			<Object Name="lvwFinanceGroups_colGroupName" Type="List">Groep Naam</Object>
			<Object Name="lvwFinanceGroups_colGroupNumber" Type="List">Groep Nummer</Object>
			<Object Name="lvwFinanceClients_colFirstName" Type="List">Voornaam</Object>
			<Object Name="lvwFinanceClients_colMiddleName" Type="List">Tussenvoegsel</Object>
			<Object Name="lvwFinanceClients_colFamilyName" Type="List">Achternaam</Object>
			<Object Name="lvwDescription_colDescriptions" Type="List">Omschrijvingen</Object>
			<Object Name="lvwDescription_colCounts" Type="List">Aantal</Object>
			<Object Name="lvwDescription_colAmounts" Type="List">Bedrag</Object>
			<Object Name="lvwDescription_colTax" Type="List">BTW</Object>
			<Object Name="lvwFinance_colDate" Type="List">Datum</Object>
			<Object Name="lvwFinance_colClient" Type="List">Klant</Object>
			<Object Name="lvwFinance_colLogin" Type="List">Login</Object>
			<Object Name="lvwFinance_colDescription" Type="List">Omschrijving</Object>
			<Object Name="lvwFinance_colCount" Type="List">Aantal</Object>
			<Object Name="lvwFinance_colBilledAmount" Type="List">Gefactureerd</Object>
			<Object Name="lvwFinance_colPayedAmount" Type="List">Betaald</Object>
			<Object Name="lvwFinance_colPayed" Type="List">Voldaan</Object>
			<Object Name="lvwFinance_colPayDate" Type="List">Laatste Bet.</Object>

			<Object Name="btnFinancePay" Type="Text">Betaal Factuur</Object>
			<Object Name="btnFinanceDelete" Type="Text">Verwijder Factuur</Object>
			<Object Name="lblFinanceDescription" Type="Text">Omschrijving</Object>
			<Object Name="lblClientName" Type="Text">Klant Naam</Object>
			<Object Name="lblGroupName" Type="Text">Groep Naam</Object>
			<Object Name="btnFinanceAdd" Type="Text">Nieuwe Factuur</Object>
			<Object Name="btnFinanceEdit" Type="Text">Facturen Beheren</Object>
			<Object Name="grpFinanceGroupPayments" Type="Text">Facturen</Object>
			<Object Name="lblFinancePayDue" Type="Text">Openstaand</Object>
			<Object Name="lblFinancePayTotal" Type="Text">Totaal</Object>

			<Object Name="tpgReports" Type="Text">Rapporten</Object>
			<Object Name="btnRepLessons" Type="Text">Lessen</Object>
			<Object Name="lblRepLimitSelection" Type="Text">Beperk tot selectie:</Object>
			<Object Name="rbnRepLimitSeason" Type="Text">Seizoen</Object>
			<Object Name="rbnRepLimitDay" Type="Text">Dag</Object>
			<Object Name="rbnRepLimitWeek" Type="Text">Week</Object>
			<Object Name="rbnRepLimitMonth" Type="Text">Maand</Object>
			<Object Name="chkRepLimitTrack" Type="Text">Baan</Object>
			<Object Name="chkRepLimitGroup" Type="Text">Groep</Object>
			<Object Name="chkRepLimitClient" Type="Text">Klant</Object>
			<Object Name="chkRepLimitInvoice" Type="Text">Factuur</Object>
			<Object Name="grpLimitType" Type="Text">Selecteer Type</Object>
			<Object Name="rbnRepLimitTypeBar" Type="Text">Bar</Object>
			<Object Name="rbnRepLimitTypeTeacher" Type="Text">Leraar</Object>
			<Object Name="rbnRepLimitTypeClient" Type="Text">klant</Object>
			<Object Name="rbnRepLimitTypeAll" Type="Text">Alles</Object>
			<Object Name="btnRepFinance" Type="Text">Financien</Object>
			<Object Name="btnRepOpenBills" Type="Text">Open Facturen</Object>
			<Object Name="btnRepPayments" Type="Text">Betalingen</Object>

			<Object Name="mnuRepFile" Type="Menu">Bestand</Object>
			<Object Name="mnuRepFileOpen" Type="Menu">Open</Object>
			<Object Name="mnuRepFileSave" Type="Menu">Opslaan</Object>
			<Object Name="mnuRepFilePrint" Type="Menu">Afdrukken</Object>
			<Object Name="mnuRepFilePrintPreview" Type="Menu">Afdruk Voorbeeld</Object>
			<Object Name="mnuRepFileNew" Type="Menu">Nieuw</Object>
			<Object Name="mnuRepFileRefresh" Type="Menu">Verversen</Object>
			<Object Name="mnuRepEdit" Type="Menu">Bewerken</Object>
			<Object Name="mnuRepEditFont" Type="Menu">Lettertype</Object>

			<Object Name="tpgSearch" Type="Text">Zoeken</Object>
			<Object Name="lbl2CharacterMinimum" Type="Text">2 tekens minimum</Object>
			<Object Name="lblSearchFirstName" Type="Text">Voornaam</Object>
			<Object Name="lblSearchLastName" Type="Text">Achternaam</Object>
			<Object Name="lblSearchPostalCode" Type="Text">Postcode</Object>
			<Object Name="lblSearchCity" Type="Text">Woonplaats</Object>
			<Object Name="lblSearchGroupName" Type="Text">Groep Naam / Nr</Object>
			<Object Name="lblSearchEmail" Type="Text">Email</Object>
			<Object Name="lblSearchPhone" Type="Text">Telefoon Nummer</Object>
			<Object Name="lblSearchDayOfBirth" Type="Text">Geboortedatum</Object>
			<Object Name="grpMatchPerItem" Type="Text">Overeenkomsten</Object>
			<Object Name="rbnPartialMatchLeft" Type="Text">Gedeeltelijk Links</Object>
			<Object Name="rbnPartialMatchAny" Type="Text">Gedeeltelijk Overal</Object>
			<Object Name="rbnExactMatch" Type="Text">Exacte Match</Object>
			<Object Name="grpMatchNumber" Type="Text">Aantal overeenkomsten</Object>
			<Object Name="rbnMatchAll" Type="Text">Alles Matchen</Object>
			<Object Name="rbnMatchAny" Type="Text">Elke Matchen</Object>
			<Object Name="lblSearchMaximum" Type="Text">Maximum Aantal</Object>
			<Object Name="btnSearch" Type="Text">Zoeken</Object>
			<Object Name="btnSearchClear" Type="Text">Wissen</Object>

			<Object Name="lvwSearchResult_colSearchName" Type="List">Naam</Object>
			<Object Name="lvwSearchResult_colSearchAddress" Type="List">Adres</Object>
			<Object Name="lvwSearchResult_colSearchPostalCode" Type="List">Postcode</Object>
			<Object Name="lvwSearchResult_colSearchCity" Type="List">Woonplaats</Object>
			<Object Name="lvwSearchResult_colSearchTelephone" Type="List">Telefoon</Object>
			<Object Name="lvwSearchResult_colSearchMobile" Type="List">Mobiel</Object>
			<Object Name="lvwSearchResult_colSearchEmail" Type="List">Email</Object>
			<Object Name="lvwSearchResult_colSearchDayOfBirth" Type="List">Geboortedatum</Object>
			<Object Name="lvwSearchResult_colSearchGroupName" Type="List">Group Naam</Object>
			<Object Name="lvwSearchResult_colSearchCountry" Type="List">Land</Object>
			<Object Name="lvwSearchResult_colSearchGroupId" Type="List">Groep Nummer</Object>

			<Object Name="strGeneralError" Type="Prop">Er is een onbekende fout opgetreden.</Object>
			<Object Name="strCheckLog" Type="Prop">Controleer de logfile voor meer informatie.</Object>
			<Object Name="strCheckSettings" Type="Prop">Controleer uw instellingen</Object>
			<Object Name="strWarning" Type="Prop">Waarschuwing</Object>
			<Object Name="strAreYouSure" Type="Prop">Weet u het zeker?</Object>
			<Object Name="strContinue" Type="Prop">Wilt u doorgaan?</Object>
			<Object Name="strLogError" Type="Prop">Er was een fout bij het schrijven naar de logfile.</Object>
			<Object Name="strDataError" Type="Prop">Er was een fout bij het verbinden met de database.</Object>
			<Object Name="strXmlError" Type="Prop">Er was een fout bij het verbinden met de XML file.</Object>
			<Object Name="strPreconfigured" Type="Prop">Alleen keuze waarden zijn toegestaan voor deze lijst</Object>
			<Object Name="strNumeric" Type="Prop">Alleen numerieke waarden zijn toegestaan.</Object>
			<Object Name="strPermanentDelete" Type="Prop">Dit verwijdert de selectie (en onderliggende waarden) permanent.</Object>
			<Object Name="strDelete1" Type="Prop">Er kan slechts 1 item tegelijk worden verwijderd.</Object>
			<Object Name="strAllData" Type="Prop">Voer alle verplichte data in voordat u op deze knop drukt.</Object>
			<Object Name="strSettingReload" Type="Prop">Voor de meeste van deze instellingen moet u TrackManager herstarten.</Object>
			<Object Name="strTime" Type="Prop">Tijd</Object>
			<Object Name="strBar" Type="Prop">Bar</Object>
			<Object Name="strClient" Type="Prop">Klant</Object>
			<Object Name="strTeacher" Type="Prop">Leraar</Object>
			<Object Name="strAdd" Type="Prop">Toevoegen</Object>
			<Object Name="strUpdate" Type="Prop">Bijwerken</Object>
			<Object Name="strYes" Type="Prop">Ja</Object>
			<Object Name="strNo" Type="Prop">Nee</Object>
			<Object Name="strGroupNotEmpty" Type="Prop">Alleen groepen zonder leden kunnen verwijderd worden.</Object>
			<Object Name="strInvoiceNotEmpty" Type="Prop">Alleen facturen zonder inhoud kunnen verwijderd worden.</Object>
		</Form>
		<Form Name="frmSettings">
			<Object Name="tpgTracks" Type="Text">Banen</Object>
			<Object Name="btnClearTrack" Type="Text">Wissen</Object>
			<Object Name="btnAddTrack" Type="Text">Toevoegen</Object>
			<Object Name="btnDeleteTrack" Type="Text">Verwijderen</Object>
			<Object Name="btnEditTrack" Type="Text">Berwerken</Object>
			<Object Name="tpgLessonTypes" Type="Text">Les Types</Object>
			<Object Name="btnClearLessonType" Type="Text">Wissen</Object>
			<Object Name="btnAddLessonType" Type="Text">Toevoegen</Object>
			<Object Name="btnDeleteLessonType" Type="Text">Verwijderen</Object>
			<Object Name="btnEditLessonType" Type="Text">Bewerken</Object>
			<Object Name="tpgLevels" Type="Text">Niveaus</Object>
			<Object Name="btnClearLevel" Type="Text">Wissen</Object>
			<Object Name="btnAddLevel" Type="Text">Toevoegen</Object>
			<Object Name="btnDeleteLevel" Type="Text">Verwijderen</Object>
			<Object Name="btnEditLevel" Type="Text">Bewerken</Object>
			<Object Name="tpgDescriptions" Type="Text">omschrijvingen</Object>
			<Object Name="btnClearDescription" Type="Text">wissen</Object>
			<Object Name="btnAddDescription" Type="Text">Toevoegen</Object>
			<Object Name="btnDeleteDescription" Type="Text">Verwijderen</Object>
			<Object Name="btnEditDescription" Type="Text">Bewerken</Object>
			<Object Name="tpgPrContacts" Type="Text">Pr Contacten</Object>
			<Object Name="btnClearPrContact" Type="Text">Wissen</Object>
			<Object Name="btnAddPrContact" Type="Text">Toevoegen</Object>
			<Object Name="btnDeletePrContact" Type="Text">Verwijderen</Object>
			<Object Name="btnEditPrContact" Type="Text">Bewerken</Object>
			<Object Name="tpgLogging" Type="Text">Loggen</Object>
			<Object Name="btnSaveSettingsLog" Type="Text">Opslaan</Object>
			<Object Name="lblLogfileName" Type="Text">Naam Logbestand</Object>
			<Object Name="lblLogfileLocation" Type="Text">Locatie Logbestand</Object>
			<Object Name="rbtLoggingLevel5" Type="Text">Alles (inclusief Database Queries)</Object>
			<Object Name="lblLoggingLevel" Type="Text">Log Niveau</Object>
			<Object Name="rbtLoggingLevel1" Type="Text">Laag (Alleen fouten)</Object>
			<Object Name="rbtLoggingLevel2" Type="Text">Medium (inclusief programma gebeurtenissen)</Object>
			<Object Name="rbtLoggingLevel3" Type="Text">Medium-Hoog (Inclusief gebruiker handelingen)</Object>
			<Object Name="rbtLoggingLevel4" Type="Text">Hoog (Ales behalve Database Queries)</Object>
			<Object Name="rbtLoggingLevel0" Type="Text">Uit (Alleen Programma Start en Beveiliging)</Object>
			<Object Name="tpgGeneral" Type="Text">Algemeen</Object>
			<Object Name="lblSeasonStart" Type="Text">Seizoen Start</Object>
			<Object Name="lblSeasonLength" Type="Text">Seizoen lengte</Object>
			<Object Name="tpgView" Type="Text">Uiterlijk</Object>
			<Object Name="lblReadOnlyBackColor" Type="Text">Aleen lezen achtergrond</Object>
			<Object Name="lblTimeFrame" Type="Text">Tijd Spanne</Object>
			<Object Name="lblDefFinanceRows" Type="Text">Minimum Financiele regels</Object>
			<Object Name="lblShowTimeWithTrack" Type="Text">Tijd bij elke baan</Object>
			<Object Name="btnSaveSettingsView" Type="Text">Opslaan</Object>
			<Object Name="lblClientsPerTrack" Type="Text">Klanten per baan</Object>
			<Object Name="lblClientsPerGroup" Type="Text">Aantal klanten per groep</Object>
			<Object Name="lblOpeningHour" Type="Text">Openings tijd</Object>
			<Object Name="lblClosingHour" Type="Text">Sluitings tijd</Object>
			<Object Name="lblShowClosedHours" Type="Text">Toon gesloten uren</Object>
			<Object Name="lblOnHoursColor" Type="Text">Openings tijden kleur</Object>
			<Object Name="lblOffHoursColor" Type="Text">Gesloten tijden kleur</Object>
			<Object Name="lblLanguage" Type="Text">Taal</Object>
			<Object Name="lblShowTeacherColumn" Type="Text">Toon Leraren kolom</Object>
			<Object Name="lblClientFieldWidth" Type="Text">Klant veld breedte</Object>
			<Object Name="lblUseFadingColors" Type="Text">Gebruik Kleurenschaal</Object>
			<Object Name="tpgDatabase" Type="Text">Database</Object>
			<Object Name="btnSaveSettingsDatabase" Type="Text">Opslaan</Object>
			<Object Name="btnUseDefaults" Type="Text">Standaard</Object>
			<Object Name="lblLoginMethod" Type="Text">Inlog Methode</Object>
			<Object Name="lblLoginName" Type="Text">Gebruikers naam</Object>
			<Object Name="lblPassword" Type="Text">wachtwoord</Object>
			<Object Name="lblDatabaseName" Type="Text">Database Naam</Object>
			<Object Name="lblDatabaseLocation" Type="Text">Database Locatie</Object>
			<Object Name="lblDataProvider" Type="Text">Data Provider</Object>
			<Object Name="btnClose" Type="Text">Sluiten</Object>
			<Object Name="lvwTracks_colTrackName" Type="List">Baan</Object>
			<Object Name="lvwTracks_colTrackOffset" Type="List">Baan Offset</Object>
			<Object Name="lvwLessonTypes_colLessonTypeName" Type="List">Les Type</Object>
			<Object Name="lvwLessonTypes_colLessonTypeColor" Type="List">Les Type Kleur</Object>
			<Object Name="lvwLevels_colLevelName" Type="List">Niveau</Object>
			<Object Name="lvwLevels_colLevelColor" Type="List">Niveau Kleur</Object>
			<Object Name="lvwLevels_colLevelCount" Type="List">Aantal Lessen</Object>
			<Object Name="lvwDescriptions_colDescription" Type="List">Omschrijving</Object>
			<Object Name="lvwDescriptions_colDescriptionCount" Type="List">Aantal</Object>
			<Object Name="lvwDescriptions_colDescriptionAmount" Type="List">Bedrag</Object>
			<Object Name="lvwDescriptions_colTax" Type="List">BTW</Object>
			<Object Name="lvwPrContacts_colPrContacts" Type="List">Pr Contacten</Object>
		</Form>
		<Form Name="frmGroups">
			<Object Name="btnClose" Type="Text">Sluiten</Object>
			<Object Name="btnClearGroup" Type="Text">Wissen</Object>
			<Object Name="btnAddGroup" Type="Text">Toevoegen</Object>
			<Object Name="btnDeleteGroup" Type="Text">Verwijderen</Object>
			<Object Name="btnEditGroup" Type="Text">Bewerken</Object>
			<Object Name="lvwGroups_colGroupName" Type="List">Groep Naam</Object>
			<Object Name="lvwGroups_colGroupNumber" Type="List">Groep Nummer</Object>
		</Form>
		<Form Name="frmClients">
			<Object Name="lblClientName" Type="Text">Klant Naam</Object>
			<Object Name="btnMoveClient" Type="Text">Verplaatsen naar Groep</Object>
			<Object Name="btnAddClient" Type="Text">Toevoegen</Object>
			<Object Name="lblGroupName" Type="Text">Groep Naam</Object>
			<Object Name="lblMailinglist" Type="Text">Meenemen in Email lijst</Object>
			<Object Name="lblMiddleName" Type="Text">Tussenvoegsel</Object>
			<Object Name="lblCustom4" Type="Text">Custom 4</Object>
			<Object Name="lblCustom3" Type="Text">custom 3</Object>
			<Object Name="lblCustom2" Type="Text">Custom 2</Object>
			<Object Name="lblCustom1" Type="Text">Custom 1</Object>
			<Object Name="lblRemarks" Type="Text">Opmerkingen</Object>
			<Object Name="lblBankaccount" Type="Text">Bankrekening</Object>
			<Object Name="lblDateOfBirth" Type="Text">Geboortedatum</Object>
			<Object Name="lblPrContact" Type="Text">Pr Contacten</Object>
			<Object Name="lblEmail" Type="Text">Email Adres</Object>
			<Object Name="lblMobile" Type="Text">Mobiele telefoon</Object>
			<Object Name="lblFax" Type="Text">Fax</Object>
			<Object Name="lblTelephone" Type="Text">Telefoon</Object>
			<Object Name="lblCountry" Type="Text">Land</Object>
			<Object Name="lblCity" Type="Text">Woonplaats</Object>
			<Object Name="lblPostalCode" Type="Text">Post Code</Object>
			<Object Name="lblHouseNumber" Type="Text">Huisnummer</Object>
			<Object Name="lblStreet" Type="Text">Straat</Object>
			<Object Name="lblFamilyName" Type="Text">Achternaam</Object>
			<Object Name="lblFirstName" Type="Text">Voornaam</Object>
			<Object Name="btnClose" Type="Text">Sluiten</Object>
			<Object Name="btnClearClient" Type="Text">Wissen</Object>
			<Object Name="btnUpdateClient" Type="Text">Bijwerken</Object>
			<Object Name="btnDeleteClient" Type="Text">Verwijderen</Object>
			<Object Name="lvwGroups_colgroupName" Type="List">Groep Naam</Object>
			<Object Name="lvwGroups_colGroupNumber" Type="List">Groep Nummer</Object>
			<Object Name="lvwClients_colFirstName" Type="List">Voornaam</Object>
			<Object Name="lvwClients_colMiddleName" Type="List">Tussenvoegsel</Object>
			<Object Name="lvwClients_colFamilyName" Type="List">Achternaam</Object>
		</Form>
		<Form Name="frmLogins">
			<Object Name="btnClose" Type="Text">Sluiten</Object>
			<Object Name="btnLoginClear" Type="Text">Wissen</Object>
			<Object Name="btnLoginDelete" Type="Text">Verwijderen</Object>
			<Object Name="btnLoginSave" Type="Text">Bijwerken</Object>
			<Object Name="btnLoginAdd" Type="Text">Toevoegen</Object>
			<Object Name="chkLoginAdd" Type="Text">Logins Toevoegen</Object>
			<Object Name="chkLoginChange" Type="Text">Logins Veranderen</Object>
			<Object Name="chkLoginDelete" Type="Text">Logins Verwijderen</Object>
			<Object Name="chkFinanceAdd" Type="Text">Facturen Toevoegen</Object>
			<Object Name="chkFinanceChange" Type="Text">Facturen Veranderen</Object>
			<Object Name="chkfinanceDelete" Type="Text">Facturen Verwijderen</Object>
			<Object Name="chkSettingsAdd" Type="Text">Instellingen Toevoegen</Object>
			<Object Name="chkSettingsChange" Type="Text">Instellingen Veranderen</Object>
			<Object Name="chkSettingsDelete" Type="Text">Instellingen Verwijderen</Object>
			<Object Name="chkGroupsDelete" Type="Text">Groepen Verwijderen</Object>
			<Object Name="chkClientsDelete" Type="Text">Klanten Verwijderen</Object>
			<Object Name="lblDateStop" Type="Text">Verloop Datum</Object>
			<Object Name="lblDateStart" Type="Text">Start Datum</Object>
			<Object Name="lblPassword" Type="Text">Wachtwoord</Object>
			<Object Name="lblLoginName" Type="Text">Login Naam</Object>
			<Object Name="chkEnabled" Type="Text">Geactiveerd</Object>
			<Object Name="lvwLoginName_colLoginName" Type="List">Login Naam</Object>
		</Form>
		<Form Name="frmFinance">
			<Object Name="btncheckInvoices" Type="Text">Controleer Facturen</Object>
			<Object Name="lblDue" Type="Text">Openstaand</Object>
			<Object Name="lblPayed" Type="Text">Betaald</Object>
			<Object Name="lblBilled" Type="Text">Gefactureerd</Object>
			<Object Name="lblPayment" Type="Text">Betaling</Object>
			<Object Name="btnDetailsAdd" Type="Text">Regel Toevoegen</Object>
			<Object Name="btnPaymentAdd" Type="Text">Toevoegen</Object>
			<Object Name="btnPaymentDelete" Type="Text">Verwijderen</Object>
			<Object Name="btnDetailsDelete" Type="Text">Verwijderen</Object>
			<Object Name="btnDetailsSave" Type="Text">Regel Bijwerken</Object>
			<Object Name="lblInvoicePayments" Type="Text">Factuur Betalingen</Object>
			<Object Name="lblInvoiceDetails" Type="Text">Factuur Regels</Object>
			<Object Name="lblInvoices" Type="Text">Facturen</Object>
			<Object Name="btnInvoicePay" Type="Text">Betaal Factuur</Object>
			<Object Name="btnInvoiceDelete" Type="Text">Verwijderen</Object>
			<Object Name="lblFinanceDescription" Type="Text">Omschrijving</Object>
			<Object Name="lblClientName" Type="Text">Klant Naam</Object>
			<Object Name="lblGroupName" Type="Text">Groep Naam</Object>
			<Object Name="btnInvoiceAdd" Type="Text">Toevoegen</Object>
			<Object Name="btnDetailsEdit" Type="Text">Regel Bewerken</Object>
			<Object Name="lvwInvoices_colInvoiceDate" Type="List">Datum</Object>
			<Object Name="lvwInvoices_colInvoiceClient" Type="List">Klant</Object>
			<Object Name="lvwInvoices_colInvoiceLogin" Type="List">Geboekt door</Object>
			<Object Name="lvwInvoices_colInvoicePayed" Type="List">Betaald</Object>
			<Object Name="lvwInvoiceLines_colLineClient" Type="List">Klant</Object>
			<Object Name="lvwInvoiceLines_colLineLogin" Type="List">Geboekt door</Object>
			<Object Name="lvwInvoiceLines_colLineDescription" Type="List">Omschrijving</Object>
			<Object Name="lvwInvoiceLines_colLineCount" Type="List">Aantal</Object>
			<Object Name="lvwInvoiceLines_colLineAmount" Type="List">Bedrag</Object>
			<Object Name="lvwInvoiceLines_colLineTax" Type="List">BTW</Object>
			<Object Name="lvwPayments_colPayDate" Type="List">Datum</Object>
			<Object Name="lvwPayments_colPayClient" Type="List">Klant</Object>
			<Object Name="lvwPayments_colPayLogin" Type="List">Geboekt door</Object>
			<Object Name="lvwPayments_colPayAmount" Type="List">Bedrag</Object>
			<Object Name="lvwFinanceGroups_colGroupName" Type="List">Groep Naam</Object>
			<Object Name="lvwFinanceGroups_colGroupNumber" Type="List">Klant Naam</Object>
			<Object Name="lvwFinanceClients_colFirstName" Type="List">Voornaam</Object>
			<Object Name="lvwFinanceClients_colMiddleName" Type="List">Tussenvoegsel</Object>
			<Object Name="lvwFinanceClients_colFamilyName" Type="List">Achternaam</Object>
			<Object Name="lvwDescription_colDescriptions" Type="List">Omschrijving</Object>
			<Object Name="lvwDescription_colCounts" Type="List">Aantal</Object>
			<Object Name="lvwDescription_colAmounts" Type="List">Bedrag</Object>
			<Object Name="lvwDescription_colTax" Type="List">BTW</Object>
		</Form>
	</Language>
</TrackManager>

